demo/__init__.py
demo/afc.py
demo/crash_log.py
demo/installation_proxy.py
demo/mobile_config.py
demo/pcapd.py
demo/screenshotr.py
demo/syslog.py
demo/instrument_demo/__init__.py
demo/instrument_demo/activity.py
demo/instrument_demo/app_lifecycle.py
demo/instrument_demo/applictionListing.py
demo/instrument_demo/channel.py
demo/instrument_demo/coreprofilesessiontap.py
demo/instrument_demo/coreprofilesessiontap_parse.py
demo/instrument_demo/demo.py
demo/instrument_demo/deviceinfo.py
demo/instrument_demo/energy.py
demo/instrument_demo/gpu.py
demo/instrument_demo/graphics.py
demo/instrument_demo/launchAPP.py
demo/instrument_demo/mobileNotifications.py
demo/instrument_demo/netstatPID.py
demo/instrument_demo/networking.py
demo/instrument_demo/sysmontap.py
demo/instrument_demo/xcuitest.py
ios_device/__init__.py
ios_device/__version__.py
ios_device/main.py
ios_device/py_ios_device.py
ios_device/cli/__init__.py
ios_device/cli/base.py
ios_device/cli/cli.py
ios_device/cli/instruments.py
ios_device/cli/mobile.py
ios_device/remote/__init__.py
ios_device/remote/remote_lockdown.py
ios_device/remote/remotexpc.py
ios_device/remote/xpc_message.py
ios_device/servers/Installation.py
ios_device/servers/Instrument.py
ios_device/servers/__init__.py
ios_device/servers/afc.py
ios_device/servers/amfi.py
ios_device/servers/crash_log.py
ios_device/servers/diagnostics_relay.py
ios_device/servers/dvt.py
ios_device/servers/house_arrest.py
ios_device/servers/image_mounter.py
ios_device/servers/mc_install.py
ios_device/servers/notification_proxy.py
ios_device/servers/os_trace.py
ios_device/servers/pcapd.py
ios_device/servers/plist_service.py
ios_device/servers/screenshotr.py
ios_device/servers/simulate_location.py
ios_device/servers/spring_board.py
ios_device/servers/syslog.py
ios_device/servers/testmanagerd.py
ios_device/util/__init__.py
ios_device/util/api_util.py
ios_device/util/bpylist2.py
ios_device/util/ca.py
ios_device/util/constants.py
ios_device/util/dtx_msg.py
pyidevice-2.4.22.dist-info/LICENSE
pyidevice-2.4.22.dist-info/METADATA
pyidevice-2.4.22.dist-info/WHEEL
pyidevice-2.4.22.dist-info/entry_points.txt
pyidevice-2.4.22.dist-info/top_level.txt
pyidevice-2.4.22.dist-info/RECORD
